public_ip/__init__.py
public_ip/_ip.py
public_ip-0.12.dist-info/LICENSE
public_ip-0.12.dist-info/METADATA
public_ip-0.12.dist-info/WHEEL
public_ip-0.12.dist-info/top_level.txt
public_ip-0.12.dist-info/RECORD
