Metadata-Version: 2.1
Name: public-ip
Version: 0.12
Summary: A Python function to get your public IP address.
Home-page: https://github.com/vterron/public-ip
Author: Víctor Terrón
Author-email: quintanar@gmail.com
License: UNKNOWN
Project-URL: Bug Tracker, https://github.com/vterron/public-ip/issues
Platform: UNKNOWN
Classifier: Programming Language :: Python :: 3
Classifier: License :: OSI Approved :: MIT License
Classifier: Operating System :: OS Independent
Classifier: Intended Audience :: Developers
Requires-Python: >=3.0
License-File: LICENSE
